CHANGES.txt
README.txt
bootstrap.py
buildout.cfg
setup.py
src/megrok/__init__.py
src/megrok.jinja.egg-info/PKG-INFO
src/megrok.jinja.egg-info/SOURCES.txt
src/megrok.jinja.egg-info/dependency_links.txt
src/megrok.jinja.egg-info/entry_points.txt
src/megrok.jinja.egg-info/namespace_packages.txt
src/megrok.jinja.egg-info/not-zip-safe
src/megrok.jinja.egg-info/requires.txt
src/megrok.jinja.egg-info/top_level.txt
src/megrok/jinja/__init__.py
src/megrok/jinja/configure.zcml
src/megrok/jinja/extensions.py
src/megrok/jinja/factory.py
src/megrok/jinja/ftesting.zcml
src/megrok/jinja/ftests/__init__.py
src/megrok/jinja/ftests/test_functional.py
src/megrok/jinja/ftests/i18n/__init__.py
src/megrok/jinja/ftests/i18n/test_i18n.py
src/megrok/jinja/ftests/i18n/test_i18n_templates/nodomain.jinja
src/megrok/jinja/ftests/i18n/test_i18n_templates/transtagtranslate.jinja
src/megrok/jinja/ftests/i18n/test_i18n_templates/underscoretranslate.jinja
src/megrok/jinja/ftests/i18n/test_i18n_templates/usingparams.jinja
src/megrok/jinja/ftests/inline/__init__.py
src/megrok/jinja/ftests/inline/test_inline.py
src/megrok/jinja/ftests/inline/test_inline_templates/macros.jinja
src/megrok/jinja/ftests/locales/po/en/test_domain.po
src/megrok/jinja/ftests/locales/po/es/test_domain.po
src/megrok/jinja/ftests/module_directory/__init__.py
src/megrok/jinja/ftests/module_directory/test_module_directory.py
src/megrok/jinja/ftests/module_directory/test_module_directory_templates/cavepainting.jinja
src/megrok/jinja/ftests/module_directory/test_module_directory_templates/jsonview.json
src/megrok/jinja/ftests/module_directory/test_module_directory_templates/macros.jinja
src/megrok/jinja/ftests/module_directory/test_module_directory_templates/sayhi.jinja
src/megrok/jinja/ftests/providers/__init__.py
src/megrok/jinja/ftests/providers/test_providers.py
src/megrok/jinja/ftests/providers/test_providers_templates/usingviewlets.jinja
src/megrok/jinja/ftests/providers/test_providers_templates/viewlet.jinja