Metadata-Version: 1.0
Name: megrok.jinja
Version: 0.1
Summary: Jinja2 templates integration in Grok
Home-page: http://svn.zope.org/megrok.jinja/
Author: Santiago Videla
Author-email: santiago.videla@gmail.com
License: ZPL
Keywords: grok Jinja2
Platform: UNKNOWN
Classifier: Development Status :: 3 - Alpha
Classifier: Environment :: Web Environment
Classifier: Intended Audience :: Developers
Classifier: License :: OSI Approved :: Zope Public License
Classifier: Programming Language :: Python :: 2.5
Classifier: Operating System :: OS Independent
Classifier: Topic :: Internet :: WWW/HTTP
